cmdrdata_openai/__init__.py
cmdrdata_openai/async_client.py
cmdrdata_openai/client.py
cmdrdata_openai/context.py
cmdrdata_openai/exceptions.py
cmdrdata_openai/logging_config.py
cmdrdata_openai/performance.py
cmdrdata_openai/proxy.py
cmdrdata_openai/py.typed
cmdrdata_openai/retry.py
cmdrdata_openai/security.py
cmdrdata_openai/tracker.py
cmdrdata_openai/validation.py
cmdrdata_openai/version_compat.py
cmdrdata_openai-0.2.1.dist-info/licenses/LICENSE
cmdrdata_openai-0.2.1.dist-info/METADATA
cmdrdata_openai-0.2.1.dist-info/WHEEL
cmdrdata_openai-0.2.1.dist-info/top_level.txt
cmdrdata_openai-0.2.1.dist-info/RECORD
