Metadata-Version: 2.4
Name: cmdrdata-openai
Version: 0.2.1
Summary: Customer tracking and usage-based billing for OpenAI APIs with arbitrary metadata support
Author-email: cmdrdata <terencenathan@gmail.com>
Maintainer-email: cmdrdata <terencenathan@gmail.com>
License: MIT License
Project-URL: Homepage, https://www.cmdrdata.ai
Project-URL: Documentation, https://github.com/cmdrdata-ai/cmdrdata-openai#readme
Project-URL: Repository, https://github.com/cmdrdata-ai/cmdrdata-openai
Project-URL: Issues, https://github.com/cmdrdata-ai/cmdrdata-openai/issues
Project-URL: Changelog, https://github.com/cmdrdata-ai/cmdrdata-openai/releases
Keywords: openai,ai,customer-tracking,usage-based-billing,fine-grained-billing,tokens,metadata,sdk,wrapper
Classifier: Development Status :: 4 - Beta
Classifier: Intended Audience :: Developers
Classifier: License :: OSI Approved :: MIT License
Classifier: Operating System :: OS Independent
Classifier: Programming Language :: Python :: 3
Classifier: Programming Language :: Python :: 3.9
Classifier: Programming Language :: Python :: 3.10
Classifier: Programming Language :: Python :: 3.11
Classifier: Programming Language :: Python :: 3.12
Classifier: Programming Language :: Python :: 3.13
Classifier: Topic :: Software Development :: Libraries :: Python Modules
Classifier: Topic :: Internet :: WWW/HTTP
Classifier: Topic :: Scientific/Engineering :: Artificial Intelligence
Requires-Python: >=3.9
License-File: LICENSE
Requires-Dist: openai>=1.0.0
Requires-Dist: httpx>=0.24.0
Requires-Dist: typing-extensions>=4.0.0; python_version < "3.10"
Provides-Extra: dev
Requires-Dist: pytest>=7.0.0; extra == "dev"
Requires-Dist: pytest-asyncio>=0.21.0; extra == "dev"
Requires-Dist: pytest-mock>=3.10.0; extra == "dev"
Requires-Dist: pytest-cov>=4.0.0; extra == "dev"
Requires-Dist: black>=23.0.0; extra == "dev"
Requires-Dist: isort>=5.12.0; extra == "dev"
Requires-Dist: mypy>=1.0.0; extra == "dev"
Requires-Dist: pre-commit>=3.0.0; extra == "dev"
Requires-Dist: safety>=3.0.0; extra == "dev"
Provides-Extra: test
Requires-Dist: pytest>=7.0.0; extra == "test"
Requires-Dist: pytest-asyncio>=0.21.0; extra == "test"
Requires-Dist: pytest-mock>=3.10.0; extra == "test"
Dynamic: license-file
